qgram/__init__.py
qgram/qgram.py
qgram-0.1.dist-info/METADATA
qgram-0.1.dist-info/WHEEL
qgram-0.1.dist-info/top_level.txt
qgram-0.1.dist-info/RECORD
