Metadata-Version: 2.4
Name: qgram
Version: 0.1
Summary: qgram is a lightweight Python library for building Telegram bots with a simple and intuitive interface. It provides decorator-based handlers for commands, text messages, and photos, along with convenient methods for sending and managing messages.
Author-email: relyadev <relyadev@gmail.com>
Keywords: telegram,bots,telegram-bots,chat,chatbot
Classifier: Programming Language :: Python :: 3
Classifier: License :: OSI Approved :: MIT License
Classifier: Operating System :: OS Independent
Requires-Python: >=3.10
